shadog/__init__.py
shadog/crypto.py
stringoline/__init__.py
stringoline/crypto.py
shadog-1.0.23.dist-info/LICENSE.txt
shadog-1.0.23.dist-info/METADATA
shadog-1.0.23.dist-info/WHEEL
shadog-1.0.23.dist-info/top_level.txt
shadog-1.0.23.dist-info/RECORD
